kppc/__init__.py
kppc/config.py
kppc/core.py
kppc/fastgl.py
kppc/glquad.py
kppc/kszpsz_config.py
kppc/new_remote_spectra.py
kppc/wignerd.py
kppc-1.0.3.dist-info/METADATA
kppc-1.0.3.dist-info/WHEEL
kppc-1.0.3.dist-info/top_level.txt
kppc-1.0.3.dist-info/RECORD
