Metadata-Version: 2.4
Name: kppc
Version: 1.0.3
Summary: kSZ/pSZ effect power spectrum calculator
Author-email: Hongbo Cai <ketchup@sjtu.edu.cn>
License: MIT
Keywords: pSZ effect,power spectrum
Classifier: Programming Language :: Python :: 3
Classifier: License :: OSI Approved :: MIT License
Classifier: Operating System :: OS Independent
Requires-Python: >=3.8
